taam_cloud/__init__.py
taam_cloud/_base_client.py
taam_cloud/_client.py
taam_cloud/_compat.py
taam_cloud/_constants.py
taam_cloud/_exceptions.py
taam_cloud/_files.py
taam_cloud/_models.py
taam_cloud/_qs.py
taam_cloud/_resource.py
taam_cloud/_response.py
taam_cloud/_streaming.py
taam_cloud/_types.py
taam_cloud/_version.py
taam_cloud/py.typed
taam_cloud/_utils/__init__.py
taam_cloud/_utils/_logs.py
taam_cloud/_utils/_proxy.py
taam_cloud/_utils/_reflection.py
taam_cloud/_utils/_streams.py
taam_cloud/_utils/_sync.py
taam_cloud/_utils/_transform.py
taam_cloud/_utils/_typing.py
taam_cloud/_utils/_utils.py
taam_cloud/lib/.keep
taam_cloud/resources/__init__.py
taam_cloud/resources/crawl.py
taam_cloud/resources/embeddings.py
taam_cloud/resources/maps.py
taam_cloud/resources/models.py
taam_cloud/resources/rerank.py
taam_cloud/resources/scrape.py
taam_cloud/resources/searches.py
taam_cloud/resources/chat/__init__.py
taam_cloud/resources/chat/chat.py
taam_cloud/resources/chat/completions.py
taam_cloud/resources/images/__init__.py
taam_cloud/resources/images/generations.py
taam_cloud/resources/images/images.py
taam_cloud/resources/suno/__init__.py
taam_cloud/resources/suno/music.py
taam_cloud/resources/suno/suno.py
taam_cloud/types/__init__.py
taam_cloud/types/client_upload_params.py
taam_cloud/types/crawl_create_params.py
taam_cloud/types/crawl_response.py
taam_cloud/types/crawl_status_response.py
taam_cloud/types/embedding_create_params.py
taam_cloud/types/map_discover_params.py
taam_cloud/types/map_response.py
taam_cloud/types/model_list_response.py
taam_cloud/types/rerank_create_params.py
taam_cloud/types/scrape_create_params.py
taam_cloud/types/scrape_response.py
taam_cloud/types/search_perform_params.py
taam_cloud/types/search_response.py
taam_cloud/types/upload_response.py
taam_cloud/types/chat/__init__.py
taam_cloud/types/chat/completion_create_params.py
taam_cloud/types/images/__init__.py
taam_cloud/types/images/generation_create_params.py
taam_cloud-1.0.0.dist-info/METADATA
taam_cloud-1.0.0.dist-info/WHEEL
taam_cloud-1.0.0.dist-info/licenses/LICENSE
taam_cloud-1.0.0.dist-info/RECORD
